colorocr/colorocr.py
colorocr/init.py
ColorOCR-0.1.0.dist-info/METADATA
ColorOCR-0.1.0.dist-info/WHEEL
ColorOCR-0.1.0.dist-info/entry_points.txt
ColorOCR-0.1.0.dist-info/top_level.txt
ColorOCR-0.1.0.dist-info/RECORD
