Metadata-Version: 2.2
Name: ColorOCR
Version: 0.1.0
Summary: A color-based OCR library using EasyOCR
Author: Aosin_MUDS
Project-URL: Repository, https://github.com/Aosin-muds/ColorOCR.git
Classifier: Programming Language :: Python :: 3
Classifier: License :: OSI Approved :: MIT License
Classifier: Operating System :: OS Independent
Requires-Python: >=3.6
Requires-Dist: easyocr
Requires-Dist: opencv-python-headless
Requires-Dist: numpy
Requires-Dist: matplotlib
